<annotation>
	<folder>train</folder>
	<filename>05611.jpg</filename>
	<path>/home/riotu/dl_gpu/models/research/object_detection/images/05611.jpg</path>
	<source>
		<database>Unknown</database>
	</source>
	<size>
		<width>1920</width>
		<height>1080</height>
		<depth>3</depth>
	</size>
	<segmented>0</segmented>
	<object>
		<name>car</name>
		<pose>Unspecified</pose>
		<truncated>0</truncated>
		<difficult>0</difficult>
		<bndbox>
			<xmin>1792</xmin>
			<ymin>710</ymin>
			<xmax>1877</xmax>
			<ymax>774</ymax>
		</bndbox>
	</object>
	<object>
		<name>car</name>
		<pose>Unspecified</pose>
		<truncated>0</truncated>
		<difficult>0</difficult>
		<bndbox>
			<xmin>1006</xmin>
			<ymin>345</ymin>
			<xmax>1135</xmax>
			<ymax>410</ymax>
		</bndbox>
	</object>
	<object>
		<name>car</name>
		<pose>Unspecified</pose>
		<truncated>0</truncated>
		<difficult>0</difficult>
		<bndbox>
			<xmin>853</xmin>
			<ymin>324</ymin>
			<xmax>935</xmax>
			<ymax>417</ymax>
		</bndbox>
	</object>
	<object>
		<name>car</name>
		<pose>Unspecified</pose>
		<truncated>0</truncated>
		<difficult>0</difficult>
		<bndbox>
			<xmin>471</xmin>
			<ymin>338</ymin>
			<xmax>550</xmax>
			<ymax>387</ymax>
		</bndbox>
	</object>
</annotation>